pygments_tsx/__init__.py
pygments_tsx/tsx.py
pygments_tsx-1.0.2.dist-info/METADATA
pygments_tsx-1.0.2.dist-info/WHEEL
pygments_tsx-1.0.2.dist-info/licenses/LICENSE
pygments_tsx-1.0.2.dist-info/RECORD
