Metadata-Version: 2.1
Name: pygments_tsx
Version: 1.0.2
Summary: A plugin for adding TSX support to Pygments based off the work of the JSX plugin.
Project-URL: Homepage, https://github.com/StartupOS/pygments_tsx
Project-URL: Bug Tracker, https://github.com/StartupOS/pygments_tsx/issues
Project-URL: Source, https://github.com/StartupOS/pygments_tsx
Author-email: Jason Nichols <github@startupos.dev>, Sean Conrad <github@startupos.dev>
License-Expression: MIT
License-File: LICENSE
Classifier: Development Status :: 4 - Beta
Classifier: License :: OSI Approved :: MIT License
Classifier: Operating System :: OS Independent
Classifier: Programming Language :: JavaScript
Classifier: Programming Language :: Python :: 3
Classifier: Topic :: Software Development
Classifier: Topic :: Text Editors
Requires-Python: >=3.9
Requires-Dist: flake8
Requires-Dist: jsx-lexer==2.0.1
Requires-Dist: pygments==2.16.1
Requires-Dist: pytest
Requires-Dist: pytest-cov
